{
  "酒类": {
    "top5": [
      {
        "brand": "茅台",
        "gmv": 181206221.5,
        "share": 53.6
      },
      {
        "brand": "国台",
        "gmv": 20438478.0,
        "share": 6.0
      },
      {
        "brand": "五粮液",
        "gmv": 11273139.5,
        "share": 3.3
      },
      {
        "brand": "2021年产",
        "gmv": 7510776.0,
        "share": 2.2
      },
      {
        "brand": "国鼎欧根纱",
        "gmv": 6544541.4,
        "share": 1.9
      }
    ],
    "top5_share": 67.1,
    "brand_count": 452
  },
  "传统滋补": {
    "top5": [
      {
        "brand": "百年堂",
        "gmv": 5431160.5,
        "share": 4.5
      },
      {
        "brand": "九蒸九晒黄精",
        "gmv": 5028464.0,
        "share": 4.1
      },
      {
        "brand": "神农金康",
        "gmv": 4582370.39,
        "share": 3.8
      },
      {
        "brand": "喜纯黄精五黑膏",
        "gmv": 4255154.16,
        "share": 3.5
      },
      {
        "brand": "悠悠燕耳",
        "gmv": 3783443.4,
        "share": 3.1
      }
    ],
    "top5_share": 18.9,
    "brand_count": 171
  },
  "生鲜": {
    "top5": [
      {
        "brand": "活蟹",
        "gmv": 5611133.1,
        "share": 4.1
      },
      {
        "brand": "肥肥优选",
        "gmv": 5342785.6,
        "share": 3.9
      },
      {
        "brand": "干仓陈化7年",
        "gmv": 4155744.5,
        "share": 3.1
      },
      {
        "brand": "净重280g/盒",
        "gmv": 3270650.12,
        "share": 2.4
      },
      {
        "brand": "如意三宝",
        "gmv": 3044995.0,
        "share": 2.2
      }
    ],
    "top5_share": 15.8,
    "brand_count": 300
  },
  "休闲食品": {
    "top5": [
      {
        "brand": "康师傅",
        "gmv": 8411627.4,
        "share": 7.6
      },
      {
        "brand": "干仓陈化7年",
        "gmv": 4643761.5,
        "share": 4.2
      },
      {
        "brand": "口口爆汁",
        "gmv": 4414003.0,
        "share": 4.0
      },
      {
        "brand": "Swiss",
        "gmv": 3296497.9,
        "share": 3.0
      },
      {
        "brand": "发11包",
        "gmv": 3107265.0,
        "share": 2.8
      }
    ],
    "top5_share": 21.7,
    "brand_count": 233
  },
  "保健食品/营养补充": {
    "top5": [
      {
        "brand": "诺特兰德",
        "gmv": 46333544.38,
        "share": 28.9
      },
      {
        "brand": "刘涛代言",
        "gmv": 13709447.0,
        "share": 8.6
      },
      {
        "brand": "贾冰推荐",
        "gmv": 11343512.3,
        "share": 7.1
      },
      {
        "brand": "林诺德",
        "gmv": 9116546.0,
        "share": 5.7
      },
      {
        "brand": "五个女博士",
        "gmv": 5661127.8,
        "share": 3.5
      }
    ],
    "top5_share": 53.7,
    "brand_count": 412
  },
  "饮料冲调": {
    "top5": [
      {
        "brand": "康新牧场",
        "gmv": 9912562.9,
        "share": 9.3
      },
      {
        "brand": "双12狂欢",
        "gmv": 8570458.6,
        "share": 8.0
      },
      {
        "brand": "两个月量升级肽",
        "gmv": 7343895.0,
        "share": 6.9
      },
      {
        "brand": "国产",
        "gmv": 5843162.6,
        "share": 5.5
      },
      {
        "brand": "可选海绵宝宝联名",
        "gmv": 4237879.6,
        "share": 4.0
      }
    ],
    "top5_share": 33.6,
    "brand_count": 148
  },
  "粮油调味速食": {
    "top5": [
      {
        "brand": "福月德",
        "gmv": 11067869.9,
        "share": 5.5
      },
      {
        "brand": "4盒装",
        "gmv": 8500418.1,
        "share": 4.3
      },
      {
        "brand": "开学季狂欢购",
        "gmv": 7406174.1,
        "share": 3.7
      },
      {
        "brand": "囤货活动推荐",
        "gmv": 3985861.65,
        "share": 2.0
      },
      {
        "brand": "瑞士Swiss",
        "gmv": 3585399.4,
        "share": 1.8
      }
    ],
    "top5_share": 17.3,
    "brand_count": 338
  },
  "乳品冷饮": {
    "top5": [
      {
        "brand": "认养一头牛",
        "gmv": 13387958.1,
        "share": 13.1
      },
      {
        "brand": "蒙牛",
        "gmv": 12545083.0,
        "share": 12.3
      },
      {
        "brand": "官方正品",
        "gmv": 9539658.4,
        "share": 9.4
      },
      {
        "brand": "澳大利亚进口",
        "gmv": 5542735.1,
        "share": 5.4
      },
      {
        "brand": "开学季",
        "gmv": 4037176.0,
        "share": 4.0
      }
    ],
    "top5_share": 44.2,
    "brand_count": 108
  },
  "茗茶": {
    "top5": [
      {
        "brand": "白大师",
        "gmv": 3035304.0,
        "share": 40.0
      },
      {
        "brand": "八马茶业",
        "gmv": 528262.0,
        "share": 7.0
      },
      {
        "brand": "镇店之宝",
        "gmv": 523266.0,
        "share": 6.9
      },
      {
        "brand": "冬藏·福韵",
        "gmv": 475345.8,
        "share": 6.3
      },
      {
        "brand": "绿色食品认证",
        "gmv": 405672.6,
        "share": 5.4
      }
    ],
    "top5_share": 65.5,
    "brand_count": 28
  },
  "宠物生活": {
    "top5": [
      {
        "brand": "小锋小志D系列",
        "gmv": 2700918.6,
        "share": 16.3
      },
      {
        "brand": "卫仕爆爆桶囤货装",
        "gmv": 1552609.46,
        "share": 9.4
      },
      {
        "brand": "温和排毛3.0",
        "gmv": 1059563.0,
        "share": 6.4
      },
      {
        "brand": "猫饭",
        "gmv": 933283.8,
        "share": 5.6
      },
      {
        "brand": "麦富迪",
        "gmv": 878782.53,
        "share": 5.3
      }
    ],
    "top5_share": 43.0,
    "brand_count": 241
  }
}